py_flaskbase/__init__.py
py_flaskbase/__main__.py
py_flaskbase/_version.py
py_flaskbase/config.py
py_flaskbase/exceptions.py
py_flaskbase/log_config.py
py_flaskbase/log_formatter.py
py_flaskbase/utils/__init__.py
py_flaskbase/utils/error_handler.py
py_flaskbase/utils/events.py
py_flaskbase/utils/healthcheck.py
py_flaskbase/utils/actions/__init__.py
py_flaskbase/utils/actions/after_actions.py
py_flaskbase/utils/actions/auth_request.py
py_flaskbase/utils/actions/before_actions.py
py_flaskbase/utils/application/__init__.py
py_flaskbase/utils/application/background.py
py_flaskbase/utils/application/gunicorn_conf.py
py_flaskbase/utils/application/standalone.py
py_flaskbase/utils/application/swagger.py
py_flaskbase/utils/metric/__init__.py
py_flaskbase/utils/metric/metrics.py
py_flaskbase/utils/metric/metrics_email.py
py_flaskbase/utils/metric/metrics_requests.py
py_flaskbase-0.0.2.dist-info/LICENSE
py_flaskbase-0.0.2.dist-info/METADATA
py_flaskbase-0.0.2.dist-info/WHEEL
py_flaskbase-0.0.2.dist-info/top_level.txt
py_flaskbase-0.0.2.dist-info/RECORD
