Metadata-Version: 2.1
Name: py-flaskbase
Version: 0.0.2
Author-email: atav928 <dev@tavnets.com>
License: GNU GENERAL PUBLIC LICENSE
Classifier: License :: OSI Approved :: MIT License
Classifier: Programming Language :: Python :: Implementation
Classifier: Programming Language :: Python :: 3.9
Classifier: Programming Language :: Python :: 3.10
Classifier: Programming Language :: Python :: 3.11
Requires-Python: <4,>=3.8
License-File: LICENSE
Requires-Dist: prometheus-client ==0.19.*
Requires-Dist: Flask ==3.0.*
Requires-Dist: Flask-Caching
Requires-Dist: requests
Requires-Dist: gunicorn
Requires-Dist: flask-swagger-ui
Requires-Dist: flask-swagger
Requires-Dist: six
Requires-Dist: python-ldap ==3.4.*
Provides-Extra: test
Requires-Dist: pytest-cov ; extra == 'test'
Requires-Dist: pytest ; extra == 'test'
Requires-Dist: pytest-mock ; extra == 'test'
Requires-Dist: unittest2 ; extra == 'test'
Requires-Dist: dataclasses ; extra == 'test'
Requires-Dist: six ; extra == 'test'
Requires-Dist: black ; extra == 'test'
Requires-Dist: pylint ; extra == 'test'
Requires-Dist: tomli ; extra == 'test'
